collegram-0.1.1.dist-info/METADATA
collegram-0.1.1.dist-info/WHEEL
collegram-0.1.1.dist-info/licenses/LICENSE
collegram/__init__.py
collegram/channels.py
collegram/client.py
collegram/json.py
collegram/media.py
collegram/messages.py
collegram/paths.py
collegram/text.py
collegram/users.py
collegram/utils.py
collegram-0.1.1.dist-info/RECORD
