Metadata-Version: 2.1
Name: collegram
Version: 0.1.1
Summary: A small example package
Author-Email: Thomas Louf <tlouf+pro@pm.me>
Classifier: Programming Language :: Python :: 3
Classifier: License :: OSI Approved :: MIT License
Classifier: Operating System :: OS Independent
Project-URL: Homepage, https://github.com/TLouf/collegram
Project-URL: Issues, https://github.com/TLouf/collegram/issues
Requires-Python: >=3.9
Requires-Dist: telethon>=1.34.0
Requires-Dist: msgspec>=0.18.6
Requires-Dist: polars>=0.20.10
Requires-Dist: fsspec>=2023.12.2
Requires-Dist: bidict>=0.23.1
Requires-Dist: cryptg; extra == "media"
Requires-Dist: python-dotenv>=0.5.1; extra == "scripts"
Requires-Dist: tqdm>=4.66.2; extra == "scripts"
Requires-Dist: lingua-language-detector>=2.0.2; extra == "scripts"
Provides-Extra: media
Provides-Extra: scripts
